MANIFEST.in
README.rst
flake8_t_bug_catcher.py
pyproject.toml
requirements.txt
setup.cfg
setup.py
flake8_t_bug_catcher.egg-info/PKG-INFO
flake8_t_bug_catcher.egg-info/SOURCES.txt
flake8_t_bug_catcher.egg-info/dependency_links.txt
flake8_t_bug_catcher.egg-info/entry_points.txt
flake8_t_bug_catcher.egg-info/not-zip-safe
flake8_t_bug_catcher.egg-info/requires.txt
flake8_t_bug_catcher.egg-info/top_level.txt
tests/__init__.py
tests/hook_test.py